{
  "project_info": {
    "project_number": "719937867729",
    "project_id": "boxwood-sandbox-440309-c3",
    "storage_bucket": "boxwood-sandbox-440309-c3.firebasestorage.app"
  },
  "client": [
    {
      "client_info": {
        "mobilesdk_app_id": "1:719937867729:android:97515f518e51b1dbde5af0",
        "android_client_info": {
          "package_name": "com.example.fisher2"
        }
      },
      "oauth_client": [
        {
          "client_id": "719937867729-plihpcoh7l3dn90ro89tgv5ap4mucvv0.apps.googleusercontent.com",
          "client_type": 1,
          "android_info": {
            "package_name": "com.example.fisher2",
            "certificate_hash": "6fe5883ff987b9e687b691b155d372aa28a12180"
          }
        },
        {
          "client_id": "719937867729-2gl0kp5um0nd7tfpa8genps43oivu4b9.apps.googleusercontent.com",
          "client_type": 3
        }
      ],
      "api_key": [
        {
          "current_key": "AIzaSyC12L9vttqgbyEu8ulRkSHSBuwLwui7uCQ"
        }
      ],
      "services": {
        "appinvite_service": {
          "other_platform_oauth_client": [
            {
              "client_id": "719937867729-2gl0kp5um0nd7tfpa8genps43oivu4b9.apps.googleusercontent.com",
              "client_type": 3
            }
          ]
        }
      }
    }
  ],
  "configuration_version": "1"
}